tp_shared_schemas/base/base_message.py
tp_shared_schemas/gibdd_service/v1/gibdd_dc_results_stream_message.py
tp_shared_schemas/passes_service/v1/passes_results_stream_message.py
tp_shared_schemas/policies_service/v1/policies_results_stream_message.py
tp_shared_schemas/rnis_check_service/v1/rnis_results_stream_message.py
tp_shared_schemas-0.2.23.dist-info/METADATA
tp_shared_schemas-0.2.23.dist-info/WHEEL
tp_shared_schemas-0.2.23.dist-info/RECORD
