Metadata-Version: 2.3
Name: tp-shared-schemas
Version: 0.2.23
Summary: Pydantic cхемы для всех проектов
Requires-Python: >=3.12
Classifier: Programming Language :: Python :: 3
Classifier: Programming Language :: Python :: 3.12
Classifier: Programming Language :: Python :: 3.13
Requires-Dist: pre-commit (>=4.2.0,<5.0.0)
Requires-Dist: pydantic (>=2.11.7,<3.0.0)
Requires-Dist: tp-helper (>=0.4.34,<0.5.0)
